[{"Year":"2015","Value":7.4,"GeoCode":null,"UNIT_MEASURE":"Percent","SERIES":"17.3.1 Official development assistance as % of GDP"},{"Year":"2016","Value":7.35,"GeoCode":null,"UNIT_MEASURE":"Percent","SERIES":"17.3.1 Official development assistance as % of GDP"},{"Year":"2017","Value":6.87,"GeoCode":null,"UNIT_MEASURE":"Percent","SERIES":"17.3.1 Official development assistance as % of GDP"},{"Year":"2018","Value":6.42,"GeoCode":null,"UNIT_MEASURE":"Percent","SERIES":"17.3.1 Official development assistance as % of GDP"},{"Year":"2019","Value":6.0,"GeoCode":null,"UNIT_MEASURE":"Percent","SERIES":"17.3.1 Official development assistance as % of GDP"},{"Year":"2020","Value":5.61,"GeoCode":null,"UNIT_MEASURE":"Percent","SERIES":"17.3.1 Official development assistance as % of GDP"}]