{"Year":["2015","2016","2017","2018","2019","2020"],"SERIES":["4.3.2 Gross enrolment rate in technical-vocational education programmes (15- to 24-year-olds)","4.3.2 Gross enrolment rate in technical-vocational education programmes (15- to 24-year-olds)","4.3.2 Gross enrolment rate in technical-vocational education programmes (15- to 24-year-olds)","4.3.2 Gross enrolment rate in technical-vocational education programmes (15- to 24-year-olds)","4.3.2 Gross enrolment rate in technical-vocational education programmes (15- to 24-year-olds)","4.3.2 Gross enrolment rate in technical-vocational education programmes (15- to 24-year-olds)"],"Reference area":[null,null,null,null,null,null],"Age":["15 to 24 years old","15 to 24 years old","15 to 24 years old","15 to 24 years old","15 to 24 years old","15 to 24 years old"],"UNIT_MEASURE":["Percent","Percent","Percent","Percent","Percent","Percent"],"GeoCode":[null,null,null,null,null,null],"Value":[0.03,2.4,4.7,7.0,9.4,11.7]}